setup.py
anorak/__init__.py
anorak/anonymizer.py
anorak/pseudonymizer.py
anorak.egg-info/PKG-INFO
anorak.egg-info/SOURCES.txt
anorak.egg-info/dependency_links.txt
anorak.egg-info/entry_points.txt
anorak.egg-info/not-zip-safe
anorak.egg-info/requires.txt
anorak.egg-info/top_level.txt
anorak/anatomy/__init__.py
anorak/anatomy/anatomy.py
anorak/cli/__init__.py
anorak/cli/main.py
anorak/datamodel/__init__.py
anorak/datamodel/base.py
anorak/dataset/__init__.py
anorak/dataset/base.py
anorak/dataset/numpy.py
anorak/dataset/pandas.py
anorak/dataset/sql.py
anorak/dp/__init__.py
anorak/dp/anonymizer.py
anorak/helpers/__init__.py
anorak/helpers/config.py
anorak/kanonymity/__init__.py
anorak/kanonymity/mondrian.py
anorak/kanonymity/partition.py
anorak/kanonymity/tests/__init__.py
anorak/kanonymity/tests/test_mondrian.py
anorak/kanonymity/tests/data/__init__.py