Metadata-Version: 1.0
Name: anorak
Version: 0.0.1a0
Summary: A data anonymiaztion toolkit for Python.
Home-page: https://github.com/7scientists/anorak
Author: Andreas Dewes - 7scientists
Author-email: andreas@7scientists.com
License: BSD-4
Platform: UNKNOWN
